SWV_AnyPeakFinder/__init__.py
SWV_AnyPeakFinder/__main__.py
SWV_AnyPeakFinder/__version__.py
SWV_AnyPeakFinder/gui.py
SWV_AnyPeakFinder/logic.py
SWV_AnyPeakFinder-1.9.0.dist-info/LICENSE
SWV_AnyPeakFinder-1.9.0.dist-info/METADATA
SWV_AnyPeakFinder-1.9.0.dist-info/WHEEL
SWV_AnyPeakFinder-1.9.0.dist-info/entry_points.txt
SWV_AnyPeakFinder-1.9.0.dist-info/top_level.txt
SWV_AnyPeakFinder-1.9.0.dist-info/RECORD
