Metadata-Version: 2.1
Name: SWV-AnyPeakFinder
Version: 1.9.0
Summary: GUI application for resolving peak heights in square-wave voltammetry datafiles.
Home-page: https://github.com/Paradoxdruid/SWVAnyPeakFinder
Author: Andrew J. Bonham
Author-email: bonham@gmail.com
License: GPLv3
Keywords: voltammetry,biosensor,science
Classifier: Programming Language :: Python :: 3
Classifier: Programming Language :: Python :: 3.6
Classifier: Programming Language :: Python :: 3.7
Classifier: Programming Language :: Python :: 3.8
Classifier: Programming Language :: Python :: 3.9
Classifier: Programming Language :: Python :: 3 :: Only
Classifier: License :: OSI Approved :: GNU General Public License v3 (GPLv3)
Classifier: Operating System :: OS Independent
Requires-Python: >=3.6
License-File: LICENSE
Requires-Dist: numpy
Requires-Dist: scipy
Requires-Dist: matplotlib
Requires-Dist: lmfit
